{"__symbolic":"module","version":4,"metadata":{"ɵa":{"__symbolic":"function"},"EvLoggerModule":{"__symbolic":"class","decorators":[{"__symbolic":"call","expression":{"__symbolic":"reference","module":"@angular/core","name":"NgModule","line":14,"character":1},"arguments":[{"imports":[{"__symbolic":"reference","module":"@angular/common","name":"CommonModule","line":16,"character":4}]}]}],"members":{},"statics":{"forRoot":{"__symbolic":"function","parameters":["config"],"value":{"ngModule":{"__symbolic":"reference","name":"EvLoggerModule"},"providers":[{"provide":{"__symbolic":"reference","name":"ɵb"},"useValue":{"__symbolic":"reference","name":"ɵa"},"deps":[{"__symbolic":"reference","name":"config"}]},{"__symbolic":"reference","name":"EvLogger"}]}},"forChild":{"__symbolic":"function","parameters":[],"value":{"ngModule":{"__symbolic":"reference","name":"EvLoggerModule"},"providers":[{"__symbolic":"reference","name":"EvLogger"}]}}}},"ɵb":{"__symbolic":"new","expression":{"__symbolic":"reference","module":"@angular/core","name":"InjectionToken","line":3,"character":32},"arguments":["loggerBase"]},"EvLogger":{"__symbolic":"class","extends":{"__symbolic":"reference","module":"everiscore","name":"Logger","line":6,"character":30},"decorators":[{"__symbolic":"call","expression":{"__symbolic":"reference","module":"@angular/core","name":"Injectable","line":5,"character":1}}],"members":{"__ctor__":[{"__symbolic":"constructor","parameterDecorators":[[{"__symbolic":"call","expression":{"__symbolic":"reference","module":"@angular/core","name":"Inject","line":7,"character":15},"arguments":[{"__symbolic":"reference","name":"ɵb"}]}]],"parameters":[{"__symbolic":"reference","module":"everiscore","name":"ILoggerBase","line":7,"character":45}]}]}}},"origins":{"ɵa":"./lib/ev-logger.module","EvLoggerModule":"./lib/ev-logger.module","ɵb":"./lib/ev-logger.services","EvLogger":"./lib/ev-logger.services"},"importAs":"everiscommons/logger"}